simulateIRAS.py
simulateIRAS-0.0.0.dist-info/LICENSE
simulateIRAS-0.0.0.dist-info/METADATA
simulateIRAS-0.0.0.dist-info/WHEEL
simulateIRAS-0.0.0.dist-info/top_level.txt
simulateIRAS-0.0.0.dist-info/RECORD
