Metadata-Version: 2.1
Name: simulateIRAS
Version: 0.0.0
Summary: A python package for simulating Infrared Reflection Absorption Spectroscopy(IRAS) measurements
Home-page: https://github.com/coconnor24/simulateIRAS
Author: coconnor24
Author-email: coconnor@g.harvard.edu
License: GPLv3
Keywords: IRAS,Surface Science,FTIR,doi:
Classifier: Development Status :: 4 - Beta
Classifier: Programming Language :: Python
Classifier: License :: OSI Approved :: BSD License
Classifier: Intended Audience :: Science/Research
Classifier: Intended Audience :: Education
Classifier: Topic :: Scientific/Engineering :: Chemistry
Classifier: Topic :: Scientific/Engineering :: Physics
Classifier: Operating System :: Microsoft :: Windows
License-File: LICENSE
Requires-Dist: numpy
Requires-Dist: scipy
